FreqAllocatorCpp.cp39-win_amd64.pyd
freq_allocator/__init__.py
freq_allocator/algorithm/__init__.py
freq_allocator/algorithm/single_qubit_allocate.py
freq_allocator/algorithm/two_qubit_allocate.py
freq_allocator/dataloader/__init__.py
freq_allocator/dataloader/load_chip.py
freq_allocator/model/__init__.py
freq_allocator/model/formula.py
freq_allocator/model/single_qubit_model.py
freq_allocator/model/two_qubit_model.py
freq_allocator/model_cpp/ChipCoupler.pyi
freq_allocator/model_cpp/ChipError.pyi
freq_allocator/model_cpp/ChipNode.pyi
freq_allocator/model_cpp/ChipQubit.pyi
freq_allocator/model_cpp/InternalState.pyi
freq_allocator/model_cpp/InternalStateSingleQubit.pyi
freq_allocator/model_cpp/InternalStateTwoQubit.pyi
freq_allocator/model_cpp/__init__.py
freq_allocator/model_cpp/chip_model.py
freq_allocator/model_cpp/single_error_model.py
freq_allocator/model_cpp/two_error_model.py
freq_allocator/stubs/FreqAllocatorCpp.pyi
freq_allocator/stubs/__init__.py
freq_allocator-0.1.666.dist-info/LICENSE
freq_allocator-0.1.666.dist-info/METADATA
freq_allocator-0.1.666.dist-info/WHEEL
freq_allocator-0.1.666.dist-info/top_level.txt
freq_allocator-0.1.666.dist-info/RECORD
